roastery/__init__.py
roastery/cli.py
roastery/config.py
roastery/edit.py
roastery/formats.py
roastery/importer.py
roastery/term.py
roastery-0.20240606.dev1.dist-info/METADATA
roastery-0.20240606.dev1.dist-info/WHEEL
roastery-0.20240606.dev1.dist-info/licenses/LICENSE
roastery-0.20240606.dev1.dist-info/RECORD
