Metadata-Version: 2.3
Name: roastery
Version: 0.20240606.dev1
Summary: Framework for Beancount plain text accounting
Author-email: Laurens Duijvesteijn <git@duijf.io>
License-File: LICENSE
Requires-Python: >=3.11
Requires-Dist: beancount>=2.0.0
Requires-Dist: fava>=1.27.0
Requires-Dist: prompt-toolkit>=3.0.0
Requires-Dist: typer>=0.12.0
